[
{"date": ["2018-10-22-Mon"], "show": ["Thunderbolt Fantasy Sword Seekers2", "That Time I Got Reincarnated as a Slime", "Golden Kamuy", "Space Battleship TIRAMISU Zwei", "Fist of the Blue Sky: Regenesis", "VOICE OF FOX", "Xuan Yuan Sword Luminary"], "time": ["3:00pm", "5:30pm", "6:30pm", "7:00pm", "7:30pm", "7:30pm", "9:00pm"]},
{"date": ["2018-10-23-Tue"], "show": ["Black Clover", "Shonen Ashibe GO! GO! Goma-chan", "THE ", " SideM  Wakeatte Mini!", "Jingai-san no Yome", "Conception", "Run with the Wind", "Mr. TONEGAWA Middle Management Blues"], "time": ["12:25pm", "1:00pm", "3:15pm", "7:00pm", "8:00pm", "8:30pm", "9:00pm"]},
{"date": ["2018-10-24-Wed"], "show": ["Yu-Gi-Oh! VRAINS", "Meow Meow Japanese History", "RErideD - Derrida, who leaps through time -", "My Sister, My Writer", "Between the Sky and Sea", "As Miss Beelzebub likes.", "Anime Recap"], "time": ["12:55pm", "1:30pm", "4:00pm", "4:30pm", "6:00pm", "8:50pm", "9:00pm"]},
{"date": ["2018-10-25-Thu"], "show": ["Anisong Station", "Merc StoriA: The Apathetic Boy and the Girl in a Bottle", "ZOMBIE LAND SAGA", "BAKUMATSU"], "time": ["2:00pm", "4:30pm", "5:30pm", "10:30pm"]},
{"date": ["2018-10-26-Fri"], "show": ["Ms. Vampire who lives in my neighborhood.", "Muhyo & Roji's Bureau of Supernatural Investigation", "Gurazeni: Money Pitch", "A Certain Magical Index III", "Hinomaru Sumo", "Angels of Death", "UzaMaid!", "JoJo's Bizarre Adventure: Golden Wind", "SENRAN KAGURA SHINOVI MASTER"], "time": ["3:00pm", "4:00pm", "4:30pm", "4:30pm", "5:00pm", "5:00pm", "5:30pm", "7:05pm", "8:15pm"]},
{"date": ["2018-10-27-Sat"], "show": ["Future Card Buddyfight Ace", "BONO BONO 3rd Season", "Ace Attorney Season 2", "RADIANT", "GOBLIN SLAYER", "SSSS.GRIDMAN"], "time": ["1:30am", "2:30am", "1:00pm", "1:15pm", "6:30pm", "7:40pm"]},
{"date": ["2018-10-28-Sun"], "show": ["GeGeGe no Kitaro (2018)", "The Journey Home", "BORUTO: NARUTO NEXT GENERATIONS", "DOUBLE DECKER! DOUG & KIRILL", "Ulysses: Jeanne d'Arc and the Alchemist Knight", "Anima Yell!", "HIMOTE HOUSE: A share house of super psychic girls", "Skull-face Bookseller Honda-san", "Tsurune"], "time": ["4:30am", "5:30am", "11:00am", "4:00pm", "4:30pm", "6:00pm", "6:45pm", "7:00pm", "7:45pm"]}
]